diambra/__init__.py
diambra/engine/__init__.py
diambra/engine/interface_pb2.py
diambra/engine/interface_pb2_grpc.py
diambra_engine-2.2.4.dist-info/METADATA
diambra_engine-2.2.4.dist-info/WHEEL
diambra_engine-2.2.4.dist-info/top_level.txt
diambra_engine-2.2.4.dist-info/RECORD
