Metadata-Version: 2.1
Name: diambra-engine
Version: 2.2.4
Summary: DIAMBRA™ Arena Engine API Client
Home-page: https://diambra.ai
Author: DIAMBRA Team
Author-email: info@diambra.ai
License: Custom
Classifier: Development Status :: 3 - Alpha
Classifier: Operating System :: OS Independent
Classifier: Programming Language :: Python
Classifier: Programming Language :: Python :: 3
Classifier: Topic :: Scientific/Engineering :: Artificial Intelligence
Classifier: Topic :: Scientific/Engineering :: Artificial Life
Classifier: Topic :: Games/Entertainment
Classifier: Topic :: Games/Entertainment :: Arcade
Classifier: Topic :: Education
Requires-Python: >=3.6
Requires-Dist: pip >=21
Requires-Dist: grpcio
Requires-Dist: protobuf <4.0dev,>=3.12.0
Requires-Dist: setuptools
